zoom_mcp/__init__.py
zoom_mcp/cli.py
zoom_mcp/server.py
zoom_mcp/auth/__init__.py
zoom_mcp/auth/zoom_auth.py
zoom_mcp/auth/zoom_auth.py.bak
zoom_mcp/resources/__init__.py
zoom_mcp/resources/recordings.py
zoom_mcp/tools/__init__.py
zoom_mcp/tools/recordings.py
iflow_mcp_osomai_zoom_mcp-0.1.0.dist-info/METADATA
iflow_mcp_osomai_zoom_mcp-0.1.0.dist-info/WHEEL
iflow_mcp_osomai_zoom_mcp-0.1.0.dist-info/entry_points.txt
iflow_mcp_osomai_zoom_mcp-0.1.0.dist-info/licenses/LICENSE
iflow_mcp_osomai_zoom_mcp-0.1.0.dist-info/RECORD
