Metadata-Version: 2.4
Name: iflow-mcp_osomai_zoom-mcp
Version: 0.1.0
Summary: A Model Context Protocol (MCP) server implementation for Zoom
Author: Zoom MCP Contributors
License: MIT License
License-File: LICENSE
Classifier: Development Status :: 3 - Alpha
Classifier: Intended Audience :: Developers
Classifier: License :: OSI Approved :: MIT License
Classifier: Programming Language :: Python :: 3
Classifier: Programming Language :: Python :: 3.11
Requires-Python: >=3.11
Requires-Dist: httpx>=0.24.0
Requires-Dist: mcp[cli]==1.3.0
Requires-Dist: pydantic>=2.0.0
Requires-Dist: pyjwt>=2.8.0
Requires-Dist: python-dotenv>=1.0.0
Requires-Dist: tabulate>=0.9.0
Provides-Extra: dev
Requires-Dist: black>=23.0.0; extra == 'dev'
Requires-Dist: isort>=5.12.0; extra == 'dev'
Requires-Dist: mypy>=1.0.0; extra == 'dev'
Requires-Dist: pytest-cov>=4.0.0; extra == 'dev'
Requires-Dist: pytest>=7.0.0; extra == 'dev'
Requires-Dist: ruff>=0.0.1; extra == 'dev'
